{"page": {"section_bu": "后妃", "section_lei": "德行", "category_path": "后妃/德行"}, "explain_rows": [{"section": "德行", "text": "原厚德载物 至柔而刚至静而方 并易 德冠后宫 列女𫝊 德著闺房 汉书 贤而有德 列女传 维德之行 毛诗 脩德之劳 邓后 德参姜任 汉书 德侔二南 魏书 以色亲以德固 列传 美于色厚于德 列传 婉嫕有节操 前汉书 婉嫕有节行 陈思 婉嫕慈孝 婉顺慈仁 汉纪 矢心柔顺 惠心渊塞 晋中兴书 清净专一 端一诚庄 列女传 训正后宫 嫔御有序 并列女𫝊 性少好学 汉书 而无险诐 诗 不欣小数 不好淫事 但当谢过 汉书 克己求愆 汉书 属以妇德而不忘付之以正而不衰 吕氏春秋 辅佐君子 诗 以匡主上 执策授亲 汉书 属以辅上 汉书 佐定天下 汉书 太姒嗣徽音则百斯男 缵女维莘 长子维行 并毛诗北堂书钞"}, {"section": "德行", "text": "增后妃专夕配以德升 天中记 辅成君德燮理阴政 合璧事𩔖 宫中化其德莫不柔雍 唐顺宗王皇后唐书 女中尧舜 翰苑新书曰宋宣仁太后垂帘日登用一时耆旧复祖宗法人以为女中尧舜 今世任姒 又曰章献刘太后尝手书赐辅臣谕以临朝愿治之意一时臣僚敬畏皆曰今世之任姒也 周南樛木之德 汇苑详注曰明成祖仁孝皇后徐氏中山王达女也帝初之国北平后理内政宫中肃然而和厚逮下有周南樛禾之德"}], "groups": []}