{"page": {"section_bu": "設官", "section_lei": "太府卿官属", "category_path": "設官/太府卿官属"}, "explain_rows": [{"section": "太府卿官属一（丞右主簿左 藏署 诸市署常平署 平准署）", "text": "原杜氏通典曰太府丞于周官为太府上士之任自后无闻梁太府丞一人陈因之后魏北齐各一人后周曰太府上士隋又曰太府丞唐因之有四人 主簿亦周官太府下士之任自后无闻梁置一人陈因之后魏亦然隋置四人唐因之减一人"}, {"section": "太府卿官属一（丞右主簿左 藏署 诸市署常平署 平准署）", "text": "增宋史曰元丰官制置丞簿各二人元符元年增置丞一人崇宁中置药局又添丞一人宣和三年减罢建炎罢太府寺绍兴元年复以章亿守太府寺丞续添置三人绍兴四年复置太府寺共三丞 续文献通考曰金置丞二人元置五人有经历知事照磨无主簿"}, {"section": "太府卿官属一（丞右主簿左 藏署 诸市署常平署 平准署）", "text": "原诸市署周官有司市下大夫掌市之理汉京兆尹属官有长安市长丞后汉则河南尹属官雒阳市长丞魏晋因之东晋则丹阳尹管之宋齐因之梁始隶太府陈因之后魏有京邑市令北齐则司州牧牧领东西市令丞后魏司市下大夫隋初京市令丞属司农炀帝改隶太府唐因之每市令一人丞二人 平准署周官有货人中士下士主平定物价秦置平准令汉因之秩六百石掌知物价及主练染作彩色后汉平准令丞隶大司农嘉平四年改平准为中准使宦者为之列于内署自是诸署悉以阉人为令丞魏少府属官有平准令宋惟掌染顺帝即位以帝讳准故曰染署齐又曰平准属少府梁陈则曰平水令丞北齐平准属司农后周曰平准中士下士隋初如北齐炀帝改隶太府唐因之令二人丞四人掌官市易 左右藏署周官有职币上士中士掌邦财之币又外府中士主泉藏有玉府掌王之金玊兵器之藏内府中士主货贿藏在内也职内上士主泉货所入盖其任也汉少府属官有中藏府令丞魏因之晋有左右藏令属少府晋江东置御史掌库曹后分库曹曰外左库内左库至宋省外左库而内左库直曰左库齐梁陈曰右藏北齐曰左右藏令属太府寺后周曰外府上士中士隋如北齐唐因之置左藏署令三人 掌库藏钱布帛杂䌽 右藏署令二人 掌铜铁毛角玩弄之物金玉珠宝香画䌽色进贡杂物 常平署汉宣帝时耿寿昌请于边郡皆筑仓谷贱时增价而籴贵时减价而粜名曰常平仓常平之名起于此也后汉明帝置常满仓晋又曰常平仓自后无闻梁亦曰常平仓而不籴粜陈因之后魏太和中虽不名曰常平亦各令官司籴贮俭则出粜隋曰常平仓唐武德中置常平监官以均天下之货 市肆腾踊则减价而出田啬丰羡则增籴而收触𩔖长之 后省监置常平署令一人掌仓粮管钥出纳粜籴凡天下仓廪和籴者为常平仓正租为正仓地子为义仓 天宝八年通计天下仓粮正收并和籴等见数凡一亿九千六百六万二千二百二十石"}, {"section": "太府卿官属一（丞右主簿左 藏署 诸市署常平署 平准署）", "text": "增宋史曰太府寺所隶官司二十有五左藏东西库以给官吏军兵奉禄赐予内藏库受岁计之馀积以待邦国非常之用奉宸库掌供内廷金玉珠宝祗候库掌受钱帛器皿衣服以备颁给赐予元丰库受诸路积剩及常平钱物凡封桩者皆入焉布库茶库杂物库以备赏给支用粮料院以法式颁诸司诸军廪禄奉料审计司审其给受之数以法式驱磨 以上即左右藏署之遗制 市易上下界以平百物以通边籴杂买务杂卖场以供宫府所需以受币馀之物而皆隶于都提举市易司汴河上下锁蔡河上下锁收舟船木筏之征店宅务掌官屋邸店出僦修造之事榷货务掌折博斛斗金帛之属交引库交引钱钞抵当所听民质取香药库石灰场以通出纳和济局惠民局以济民疾 以上即诸市署平准署之遗法常平署隶司农详司农卿 续文献通考曰金太府监官属左右藏库使支应所都监太仓使酒坊使典给署市卖司平准务各使皆隶焉 典给署本钩盾署古属司农寺金初曰钩盾使明昌三年改掌宫中所用薪炭冰烛 又曰元太府监官属内藏库提点大使副使左右藏库提点大使副使掌出纳御用诸王缎匹纱罗香货及收支金玉并和买纱罗布绢丝锦木棉衣服等物"}, {"section": "太府卿官属二", "text": "原汉书曰赵广汉廉洁下士有名誉州郡举茂才为平准令"}, {"section": "太府卿官属二", "text": "增唐书曰天授中裴守贞为司府丞推覈诏狱多裁恕全免数十姓不合武后旨出为汴州司马 宋史曰李孟傅参知政事李光幼子也光南谪之日才六岁以光遗表恩累官至太府丞韩侂胄欲见之孟傅曰行年六十去计已决不敢闻也孟傅博学多闻持身甚严时推能世其家"}], "groups": []}