{"page": {"section_bu": "武功", "section_lei": "军师", "category_path": "武功/军师"}, "explain_rows": [{"section": "军师", "text": "增西伯载与俱归 史记西伯将出猎卜之曰所获非龙非螭非虎非罴霸王之辅于是西伯猎果遇太公与语大悦载与俱归立为师"}, {"section": "军师", "text": "原坐谋辎车中 又魏伐赵赵急请救于齐齐威王欲将孙膑膑辞谢曰刑馀之人不可于是乃以田忌为将而孙子为师居辎车中坐为计谋大破魏军 有孔明犹鱼有水 蜀志先主曰孤之有孔明犹鱼之有水时孙权拥军在柴桑亮说权权即遣周瑜等随亮诣先主并力拒曹操操败于赤壁先主遂收江南以亮为军师中郎将成都平以亮为军师将军 谋谟帷幄 魏志荀攸字公达曹公素闻攸名与语大悦谓荀彧钟繇曰公达非常人也吾得与之计事天下当何忧哉以为军师攸深密有智防自从曹公征伐常谋谟帷幄时人子弟莫知其所言 杖节立军门 晋书魏朝以诸葛亮侨军远出利在急战每命司马懿持重以候其变亮数挑 战懿不出因遗懿巾帼妇人之饰懿怒表请决战不许乃遣卫尉辛毗杖节为军师以制之后亮复来挑战懿将出兵以应之毗杖节立军门乃止"}, {"section": "军师", "text": "增令诸将尽拜 名山藏刘基字伯温时太祖称吴公闻基言大悦称先生而不名陈友谅声势大震诸将多恐议降议奔基曰请赐臣剑先斩议降及奔者臣乃言吴公于是赐基剑令诸将尽拜基为军师有不服者斩之诸将悚然是以有龙江之捷"}], "groups": []}