{"page": {"section_bu": "巧藝", "section_lei": "塞", "category_path": "巧藝/塞"}, "explain_rows": [{"section": "塞一", "text": "原说苑塞行棋相塞谓之塞也 管子秋行五政一曰秋禁二曰博塞 庄子臧与谷相与牧羊而俱亡其羊问臧奚事挟策读书问榖奚事博塞以游事业不同亡羊均也 汉书吾丘寿王以格五召待诏 注乘五阁不得行故曰格五也又曰塞博类也不用箭但行枭散又曰格五行塞白乘至五格不得行又曰今之戏塞塞音先代反 增鲍宏塞经塞有四采塞四乘五是也 又曰行五道而投琼曰博不投琼曰塞塞亦博类"}, {"section": "塞二", "text": "原穆天子传天子北入邴与井公塞也 齐书沈文季字仲达吴兴武康人尤善塞用五子"}, {"section": "塞二", "text": "增孔帖唐韦安石侍宴殿下易之引蜀商宋霸子等博塞后前安石奏商等贱类不当戏殿上顾左右引出"}, {"section": "塞三", "text": "原赋后汉边孝先塞赋曰可以代博奕者曰塞其次也试习其术以惊睡救寐免昼寝之讥而已然而徐核其困通之极乃亦精妙而足美也故书其较略举其指归以明博奕无以尚焉曰始作塞者其明哲乎故其用物也约其为乐也大犹土鼓块枹空桑之瑟质朴之化上古所耽也然本其规模制作有式四道交正时之则也棋有十二律吕极也人操厥半六爻列也赤白色者分阴阳也乍亡乍存像日月也行必正直合道中也趋耦方折礼之容也迭往迭来刚柔通也周则复始乾行健也局平以正坤德顺也然则塞之为义盛矣大矣广矣博矣质象于天阴阳在焉取则于地刚柔分焉施之于人仁义载焉考之古今王霸备焉览其成败为法式焉增书唐张籍与昌黎书曰商论之际或不容人之短如在私尚胜者亦有累也况为博塞之戏与人竞财乎废弃时日不识其然愿绝博塞之好"}], "groups": []}