{"page": {"section_bu": "設官", "section_lei": "左右千牛", "category_path": "設官/左右千牛"}, "explain_rows": [{"section": "左右千牛一", "text": "原杜氏通典曰千牛刀名后魏有千牛备身掌执御刀因以名职 谢绰宋拾遗有千牛刀即人君防身刀也齐尚书杨玉夫取千牛刀杀苍梧王是也其义盖取庄子云庖丁为文惠君解牛十九年所割数千牛而刀刃若新发于硎因以为备身刀名也 北齐千牛备身属左右将军隋有左右领左右府大将军一人将军二人掌侍卫左右供御兵仗领千牛备身十二人掌执千牛刀备身左右十二人掌供御刀箭备身十六人掌宿卫侍从 左右置长史司马录事及仓兵二曹参军事铠曹行参军 炀帝改左右领左右府为左右备身府置备身郎将等官唐贞观中复为左右领左右府显庆五年始置左右千牛府龙朔二年改左右千牛府为左右奉宸卫后改为左右千牛卫神龙二年各置大将军二人 初以安国相王为千牛卫大将军是时王以尝登帝位 所掌与隋同总判卫事将军各一人以副之中郎将各一人通判卫事 领官属即隋左右领左右府长史以下唐改之 左右千牛备身各十二人 龙朔中改为左右奉裕咸亨初复旧垂拱二年又改为奉裕神龙元年复旧 掌执御刀宿卫侍从 皆以高荫子弟年少姿容美丽者补之花钿绣服衣绿执象笏为贵胄起家之良送 备身左右十二人 执御刀弓箭宿卫侍省 备身各一百人 掌宿卫侍从"}, {"section": "左右千牛一", "text": "增宋史职官志曰环卫官有左右千牛卫上将军大将军将军 续文献通考曰辽南面有左右千牛卫设官与金吾同金元无"}, {"section": "左右千牛二", "text": "增玉海曰永徽六年褚遂良请千牛不简嫡庶 左千牛韦待价左千牛备身崔知温右千牛韦武王方翼 又曰宋奉宸队即唐千牛卫营尝更是名广朝黄麾为近仗称亲扈 册府元龟曰杨义臣秦国县公崇之子也崇击突厥力战而死义臣袭崇官开皇中年未弱冠奉诏侍卫如千牛者数年赏赐甚厚"}, {"section": "左右千牛三", "text": "增制唐钱珝授前威勇军节度都指挥使杨承袭左千牛卫大将军制曰具官杨承袭素以材力闻于朝廷皆属兴师乃思致勇而时惟黩武未足经邦每念残人遂能屈已既从休息何必训齐尔其罢彼戎机来归环卫职亲任重假宠任多无怀逆命之谋宜奉徵还之召况参宿卫亦在促装 又授前千牛卫将军徐棨右神武将军兼知军事等制曰敕具官徐棨等陈力诸吏曳长组于西阶之下而参将军之位者况假地官之秩兼骑省之名仕盖显矣惟棨暨岊皆尝立朝自效之勤所闻甚著使之迁推乃用旧章道邻有劳于公亦宜赋禄郡佐渐优之命勉进尔途"}], "groups": []}