{"page": {"section_bu": "設官", "section_lei": "京府推官", "category_path": "設官/京府推官"}, "explain_rows": [{"section": "京府推官", "text": "增察其冤诬 宋史云五代漠初魏王承训为开封府尹卢亿以水布郎中充推官时侍卫诸军骄恣军士成美以驴负盐入都门阍者不敢执反擒平民孟柔送侍卫司柔自诬服论死亿察其冤言于汉祖而释之 反坐告者 又曰神宗时蔡齐子延庆以集贤校理历开封府推官有卫士告黄衣老卒筒火入直延庆察卒辞色疑焉询之果诬即反坐告者事闻帝甚重之 文擢第一 又曰毕仲游宰相士安曾孙也召试学士院同策问者九人乃黄庭坚晁补之辈苏轼异其文擢为第一加集贤校理开封府推官 不伐科名 又曰真宗尹京杨砺为推官真宗尝问砺以何年及第砺唯唯不对后知其唱名第一自悔失问谓砺不以科名自伐甚重之 伉直尚气 又曰王益柔曙子也伉直尚气以荫至集贤校理与苏舜钦秦邸会醉作傲歌时人欲遂倾正党至列状言益柔罪当诛韩琦为解于帝久之为开封府推官 请察狱冤 又云李防擢开封府推官请与判官间三五日即府司军巡院察冤狱 特加叹赏 又云乔维岳为淮南转运副使尝按部至泗州虑囚法掾误断囚至死维岳诘之掾 俯伏且泣曰有母年八十馀今获罪则母不能活矣维岳悯之因谓曰他日朝制按事第云转运使令处兹罪卒如其言获免维岳坐赎金百二十斤罢使职权知楚州真宗以寿王尹京精择府僚召还为开封府推官或言其在淮南决狱不平左右有知其事者辩之太宗特加叹赏京府事维岳平处详敏有王陟为司录真宗亦称其名干及践阼即命维岳与毕士安权知开封府 法不止笞 又云吕公孺为开封府推官民鬻薪为盗所夺逐之遭伤时包拯为尹命笞盗公孺曰盗而伤主法不止笞执不从拯善其守 事宜穷治 又云韩绛为开封府推官有男子冷青妄称其母顷在掖庭得幸有娠而出生已府以为狂奏流汝州绛言留之在外恐惑众追责穷治盖其母尝执役宫禁嫁民冷绪生一女乃生青遂论弃市 奏事赐绯 又云赵槩少笃学器识宏远为一时名辈称许中进士为集贤校理授开封府推官奏事殿中仁宗面赐银绯 未午而毕 又云杨绘为开封府推官遇事迎刃而解诸吏惟日不足绘未午率沛然 决断精敏声闻益远 又云王安石不悦苏轼令权开封府推官将困之以事轼决断 精敏声闻益远 创立推判分治之法 又云元祐中王岩叟为枢密都承旨权知开封府旧以推判官二人分左右厅共治一事多为异同岩叟创立逐官分治之法自是著为令"}], "groups": []}