{"page": {"section_bu": "武功", "section_lei": "宗族从军", "category_path": "武功/宗族从军"}, "explain_rows": [{"section": "宗族从军一", "text": "增魏志李典传曰太祖与袁绍相拒官渡典率宗族及部曲输榖帛供军 唐书浑瑊传曰瑊年十一善骑射随父释之防秋朔方节度使张齐丘戏曰与乳媪俱来邪是岁立跳荡功"}, {"section": "宗族从军二", "text": "原萧何遣 耿纯率 何遣宗族子弟从军侍汉王三后汉耿绳字伯山率宗族宾客 千人从世祖恐宾客等有异心乃烧其庐舍以绝反顾之望 举宗从魏 收族诣邺 魏志韦成宗族三千人家居乘氏请从魏郡太祖曰卿欲慕耿纯耶谢曰臣功微宠过举宗陈力今征伐未息宜实郊隧非敢望纯云云邺臧霸率子弟请收族属诣"}, {"section": "宗族从军二", "text": "增五服子弟三百人甥侄部曲二百人 南史曹景宗传曰梁武表景宗为竟陵太守及帝起兵景宗聚众率五服内子弟三百人从军曲唐书史敬奉传曰敬奉矛矢在手前无强敌甥侄部 二百人每出辄分其队为四五随水草数日不相知及相遇已皆有获 请子率奴马从军 请家出奴马助征 又兵志曰郭子仪之婿端王傅吴仲孺殖赀累巨万闻国家有急不自安请以子率奴马从军德宗喜甚为官其子五品出白志贞请节度都团练观察使与世尝任者家皆家 子弟奴马装铠助征授官如仲儒子于是豪富者缘为幸而贫者苦之"}, {"section": "宗族从军三", "text": "增诗唐杜甫览柏中丞并子侄数人除官制词诗曰纷然丧乱际见此忠孝门蜀中寇亦甚柏氏功弥存深诚补王室戮力自元昆三止锦江沸独清玉垒昏高名入竹帛新渥照乾坤子弟先卒伍芝兰叠玙璠同心注师律洒血在戎轩"}], "groups": []}