{"page": {"section_bu": "邊塞", "section_lei": "扶南诸小国", "category_path": "邊塞/扶南诸小国"}, "explain_rows": [{"section": "扶南诸小国（蒲罗中国马优钹国薄横跌国比攎国 五州 叹州 耽兰州斯调国 巨延洲林阳国 滨那专国 乌文国）", "text": "增太平御览曰吴时康泰为中郎表上扶南土俗曰东行极崎头海边有居人人皆有尾五六寸名蒲罗中国其俗食人 优钹国者在天竺之东南可五千里国土炽盛城郭珍玩谣俗与扶南同 横跌国在优钹之东南城郭饶乐不及优钹也 诸薄之东南有比攎洲出锡卖与外徼 诸薄之东有马五洲出鸡舌香树木多华少实 诸薄之西北有薄叹洲土地出金常以采金为业转卖与诸贾人易粮米杂物 诸薄之西北有耽兰之洲出铁 诸薄之东北有巨延州人民无田种芋浮船海中截大蚶螺杯往扶南 滨那专国出 都田切 马及金俗民皆有衣被结发也 乌文国昔混滇初载贾人大舶入海所成此国 斯调洲湾中有自然盐累如细石子国人取之一车输王馀自入 扶南之西南有林阳国去扶南七千里土地奉佛有数千沙门持戒大斋日鱼肉不得入国一日再市朝市诸杂米甘果石蜜暮中但香花"}], "groups": []}