{"page": {"section_bu": "靈異", "section_lei": "神异", "category_path": "靈異/神异"}, "explain_rows": [{"section": "神异", "text": "原王猛卖畚 王猛少贫鬻畚洛阳有一人贵买之而无直猛利其直从行不觉入深山见一老父踞胡床左右十数人引猛进拜之父云王公何缘拜也乃十倍偿畚价猛出反顾乃嵩山也 应妪得金 应妪者生四子而寡见神光照袂试探之乃得金自是诸子官崇并有才名至应玚七世通显也 糜竺失火 蜀志糜竺字子仲东海人资累巨万从洛还家行未到数十里路傍逢一妇人求车 寄载行二十里妇人谢去曰天使我往东海烧糜竺家感君义故相告竺恳请之曰不可不烧君快去我缓行竺急归尽出财日中果火发 管宁神光 管宁就徵将家属行夜黑无人见有火炉前引人以为神光助积善之应也 陆云宿王弼墓 晋书云陆云字士龙将宿故人家夜暗迷路忽草中有光趋之至一家寄宿见一少年美风姿共谈老子辞致清远晓辞去至故人家云此处数十里无人居却寻乃至王弼墓云自此谈元大胜 嵇康受广陵散 嵇康夜宿华亭弹琴夜半有客诣之共谈音律辞致清辨谓广陵散调绝伦遂授康仍誓不得传康撰高士传"}], "groups": []}