{"page": {"section_bu": "藥", "section_lei": "款冬", "category_path": "藥/款冬"}, "explain_rows": [{"section": "款冬一", "text": "原本草经曰款冬一名颗冬一名兔奚生常山 尔雅曰菟奚颗涷生水中花紫赤 范子曰款冬花出三辅 吴氏本草曰款冬十二月开花黄白茎紫赤 述征记曰洛水至岁末凝厉则款冬花茂悦层冰之中 董仲舒曰葶苈枯于盛夏款冬华于严冬"}, {"section": "款冬二", "text": "原赋晋傅咸款冬花赋曰惟兹奇卉款冬而生原厥物之载育禀淳粹之至精用能托体固阴利此坚贞恶朱紫之相夺患居众之易倾在万物之并作故韬华而弗逞逮皆死以枯槁独保质以全形"}, {"section": "款冬二", "text": "增又曰余曾逐禽登于北山于时仲冬之月也冰凌盈谷积雪被崖顾见款冬炜然始敷因为赋曰华艳春晖既丽且殊以坚冰为膏壤吸霜雪以自濡非天然之真贵曷能弥寒暑而不渝"}, {"section": "款冬二", "text": "原赞晋郭璞款冬赞曰吹万不同阳煦阴蒸款冬之生擢颖坚冰物体所安焉知涣凝"}], "groups": []}